tracardi_profile_segmentation/plugin.py
tracardi_profile_segmentation/model/__init__.py
tracardi_profile_segmentation/model/configuration.py
tracardi_profile_segmentation/model/__pycache__/__init__.cpython-38.pyc
tracardi_profile_segmentation/model/__pycache__/configuration.cpython-38.pyc
tracardi_profile_segmentation/test/manual_test.py
tracardi_profile_segmentation-0.1.dist-info/LICENSE.md
tracardi_profile_segmentation-0.1.dist-info/METADATA
tracardi_profile_segmentation-0.1.dist-info/WHEEL
tracardi_profile_segmentation-0.1.dist-info/top_level.txt
tracardi_profile_segmentation-0.1.dist-info/RECORD
