Metadata-Version: 2.1
Name: tracardi-profile-segmentation
Version: 0.1
Summary: This plugin will add/remove segment from the profile.
Home-page: UNKNOWN
Author: Risto Kowaczewski
Author-email: risto.kowaczewski@gmail.com
License: UNKNOWN
Keywords: tracardi,plugin
Platform: UNKNOWN
Classifier: Programming Language :: Python :: 3
Classifier: License :: OSI Approved :: MIT License
Classifier: Operating System :: OS Independent
Requires-Python: >=3.8
License-File: LICENSE.md
Requires-Dist: tracardi-plugin-sdk (>=0.6.25)
Requires-Dist: tracardi
